<theme>

	<formatVersion>4</formatVersion>

	<!-- color b4897a -->

	<view name="system">
	
		<image name="background" extra="true" />
	
		<image name="system_carousel_background" extra="true">
			<color>b4897a</color>
		</image>
		
		<image name="system_carousel_border" extra="true">
			<color>b4897a</color>
		</image>
		
	</view>
	
	<view name="basic, detailed">

		<image name="gamelist_background" extra="true">
			<color>b4897a</color>
		</image>
	
		<textlist name="gamelist">
			<selectorColor>b4897a</selectorColor>
		</textlist>
		
		<image name="gamelist_border" extra="true">
			<color>b4897a</color>
		</image>
	 
	</view>
	
</theme>